{
    "3": {
        "1": [
            {
                "start": 0,
                "end": 210,
                "name": "Пропустить заставку"
            },
            {
                "start": 3370,
                "end": 3442,
                "name": "Пропустить титры"
            }
        ],
        "2": [
            {
                "start": 380,
                "end": 448,
                "name": "Пропустить заставку"
            },
            {
                "start": 3657,
                "end": 3735,
                "name": "Пропустить титры"
            }
        ],
        "3": [
            {
                "start": 289,
                "end": 363,
                "name": "Пропустить заставку"
            },
            {
                "start": 3587,
                "end": 3661,
                "name": "Пропустить титры"
            }
        ],
        "4": [
            {
                "start": 465,
                "end": 535,
                "name": "Пропустить заставку"
            },
            {
                "start": 3055,
                "end": 3124,
                "name": "Пропустить титры"
            }
        ],
        "5": [
            {
                "start": 153,
                "end": 220,
                "name": "Пропустить заставку"
            },
            {
                "start": 3745,
                "end": 3817,
                "name": "Пропустить титры"
            }
        ],
        "6": [
            {
                "start": 201,
                "end": 267,
                "name": "Пропустить заставку"
            },
            {
                "start": 3582,
                "end": 3655,
                "name": "Пропустить титры"
            }
        ],
        "7": [
            {
                "start": 214,
                "end": 285,
                "name": "Пропустить заставку"
            },
            {
                "start": 3399,
                "end": 3471,
                "name": "Пропустить титры"
            }
        ],
        "8": [
            {
                "start": 267,
                "end": 334,
                "name": "Пропустить заставку"
            },
            {
                "start": 3788,
                "end": 3862,
                "name": "Пропустить титры"
            }
        ],
        "9": [
            {
                "start": 341,
                "end": 410,
                "name": "Пропустить заставку"
            },
            {
                "start": 2740,
                "end": 2812,
                "name": "Пропустить титры"
            }
        ],
        "10": [
            {
                "start": 599,
                "end": 667,
                "name": "Пропустить заставку"
            },
            {
                "start": 4894,
                "end": 4955,
                "name": "Пропустить титры"
            }
        ]
    },
    "4": {
        "1": [
            {
                "start": 600,
                "end": 680,
                "name": "Пропустить заставку"
            },
            {
                "start": 3840,
                "end": 3938,
                "name": "Пропустить титры"
            }
        ],
        "2": [
            {
                "start": 230,
                "end": 303,
                "name": "Пропустить заставку"
            },
            {
                "start": 3062,
                "end": 3156,
                "name": "Пропустить титры"
            }
        ],
        "3": [
            {
                "start": 92,
                "end": 166,
                "name": "Пропустить заставку"
            },
            {
                "start": 4125,
                "end": 4218,
                "name": "Пропустить титры"
            }
        ],
        "4": [
            {
                "start": 111,
                "end": 188,
                "name": "Пропустить заставку"
            },
            {
                "start": 3440,
                "end": 3534,
                "name": "Пропустить титры"
            }
        ],
        "5": [
            {
                "start": 198,
                "end": 276,
                "name": "Пропустить заставку"
            },
            {
                "start": 3253,
                "end": 3347,
                "name": "Пропустить титры"
            }
        ],
        "6": [
            {
                "start": 232,
                "end": 305,
                "name": "Пропустить заставку"
            },
            {
                "start": 3236,
                "end": 3330,
                "name": "Пропустить титры"
            }
        ],
        "7": [
            {
                "start": 184,
                "end": 257,
                "name": "Пропустить заставку"
            },
            {
                "start": 2485,
                "end": 2579,
                "name": "Пропустить титры"
            }
        ],
        "8": [
            {
                "start": 361,
                "end": 438,
                "name": "Пропустить заставку"
            },
            {
                "start": 3015,
                "end": 3109,
                "name": "Пропустить титры"
            }
        ],
        "9": [
            {
                "start": 229,
                "end": 303,
                "name": "Пропустить заставку"
            },
            {
                "start": 2674,
                "end": 2768,
                "name": "Пропустить титры"
            }
        ],
        "10": [
            {
                "start": 170,
                "end": 250,
                "name": "Пропустить заставку"
            },
            {
                "start": 4515,
                "end": 4609,
                "name": "Пропустить титры"
            }
        ]
    }
}