{
    "1": {
        "1": [
            {
                "start": 0,
                "end": 7,
                "name": "Пропустить заставку"
            },
            {
                "start": 2631,
                "end": 2660,
                "name": "Пропустить титры"
            }
        ],
        "2": [
            {
                "start": 0,
                "end": 75,
                "name": "Пропустить заставку"
            },
            {
                "start": 2537,
                "end": 2573,
                "name": "Пропустить титры"
            }
        ],
        "3": [
            {
                "start": 0,
                "end": 64,
                "name": "Пропустить заставку"
            },
            {
                "start": 2465,
                "end": 2503,
                "name": "Пропустить титры"
            }
        ],
        "4": [
            {
                "start": 0,
                "end": 9,
                "name": "Пропустить заставку"
            },
            {
                "start": 2532,
                "end": 2572,
                "name": "Пропустить титры"
            }
        ],
        "5": [
            {
                "start": 0,
                "end": 48,
                "name": "Пропустить заставку"
            },
            {
                "start": 2477,
                "end": 2515,
                "name": "Пропустить титры"
            }
        ],
        "6": [
            {
                "start": 0,
                "end": 39,
                "name": "Пропустить заставку"
            },
            {
                "start": 2541,
                "end": 2578,
                "name": "Пропустить титры"
            }
        ],
        "7": [
            {
                "start": 0,
                "end": 59,
                "name": "Пропустить заставку"
            },
            {
                "start": 2536,
                "end": 2584,
                "name": "Пропустить титры"
            }
        ],
        "8": [
            {
                "start": 0,
                "end": 24,
                "name": "Пропустить заставку"
            },
            {
                "start": 2490,
                "end": 2527,
                "name": "Пропустить титры"
            }
        ],
        "9": [
            {
                "start": 0,
                "end": 46,
                "name": "Пропустить заставку"
            },
            {
                "start": 2536,
                "end": 2572,
                "name": "Пропустить титры"
            }
        ],
        "10": [
            {
                "start": 0,
                "end": 24,
                "name": "Пропустить заставку"
            },
            {
                "start": 2538,
                "end": 2576,
                "name": "Пропустить титры"
            }
        ],
        "11": [
            {
                "start": 0,
                "end": 7,
                "name": "Пропустить заставку"
            },
            {
                "start": 2502,
                "end": 2540,
                "name": "Пропустить титры"
            }
        ],
        "12": [
            {
                "start": 0,
                "end": 38,
                "name": "Пропустить заставку"
            },
            {
                "start": 2537,
                "end": 2574,
                "name": "Пропустить титры"
            }
        ],
        "13": [
            {
                "start": 0,
                "end": 51,
                "name": "Пропустить заставку"
            },
            {
                "start": 2531,
                "end": 2568,
                "name": "Пропустить титры"
            }
        ]
    },
    "3": {
        "1": [
            {
                "start": 0,
                "end": 4,
                "name": "Пропустить заставку"
            },
            {
                "start": 2840,
                "end": 2881,
                "name": "Пропустить титры"
            }
        ],
        "2": [
            {
                "start": 0,
                "end": 4,
                "name": "Пропустить заставку"
            },
            {
                "start": 3038,
                "end": 3073,
                "name": "Пропустить титры"
            }
        ],
        "3": [
            {
                "start": 0,
                "end": 5,
                "name": "Пропустить заставку"
            },
            {
                "start": 2682,
                "end": 2720,
                "name": "Пропустить титры"
            }
        ],
        "4": [
            {
                "start": 0,
                "end": 4,
                "name": "Пропустить заставку"
            },
            {
                "start": 2925,
                "end": 2961,
                "name": "Пропустить титры"
            }
        ],
        "5": [
            {
                "start": 0,
                "end": 5,
                "name": "Пропустить заставку"
            },
            {
                "start": 2926,
                "end": 2963,
                "name": "Пропустить титры"
            }
        ],
        "6": [
            {
                "start": 0,
                "end": 4,
                "name": "Пропустить заставку"
            },
            {
                "start": 2643,
                "end": 2678,
                "name": "Пропустить титры"
            }
        ],
        "7": [
            {
                "start": 0,
                "end": 5,
                "name": "Пропустить заставку"
            },
            {
                "start": 3110,
                "end": 3150,
                "name": "Пропустить титры"
            }
        ],
        "8": [
            {
                "start": 0,
                "end": 5,
                "name": "Пропустить заставку"
            },
            {
                "start": 2972,
                "end": 3009,
                "name": "Пропустить титры"
            }
        ],
        "9": [
            {
                "start": 0,
                "end": 5,
                "name": "Пропустить заставку"
            },
            {
                "start": 2994,
                "end": 3029,
                "name": "Пропустить титры"
            }
        ],
        "10": [
            {
                "start": 0,
                "end": 5,
                "name": "Пропустить заставку"
            },
            {
                "start": 3362,
                "end": 3399,
                "name": "Пропустить титры"
            }
        ]
    },
    "4": {
        "1": [
            {
                "start": 0,
                "end": 73,
                "name": "Пропустить заставку"
            },
            {
                "start": 3319,
                "end": 3381,
                "name": "Пропустить титры"
            }
        ],
        "2": [
            {
                "start": 0,
                "end": 8,
                "name": "Пропустить заставку"
            },
            {
                "start": 3274,
                "end": 3326,
                "name": "Пропустить титры"
            }
        ],
        "3": [
            {
                "start": 0,
                "end": 5,
                "name": "Пропустить заставку"
            },
            {
                "start": 3044,
                "end": 3308,
                "name": "Пропустить титры"
            }
        ],
        "4": [
            {
                "start": 0,
                "end": 5,
                "name": "Пропустить заставку"
            },
            {
                "start": 3498,
                "end": 3552,
                "name": "Пропустить титры"
            }
        ],
        "5": [
            {
                "start": 0,
                "end": 6,
                "name": "Пропустить заставку"
            },
            {
                "start": 2583,
                "end": 2630,
                "name": "Пропустить титры"
            }
        ],
        "6": [
            {
                "start": 0,
                "end": 6,
                "name": "Пропустить заставку"
            },
            {
                "start": 3176,
                "end": 3518,
                "name": "Пропустить титры"
            }
        ],
        "7": [
            {
                "start": 0,
                "end": 5,
                "name": "Пропустить заставку"
            },
            {
                "start": 3263,
                "end": 3321,
                "name": "Пропустить титры"
            }
        ],
        "8": [
            {
                "start": 0,
                "end": 5,
                "name": "Пропустить заставку"
            },
            {
                "start": 3291,
                "end": 3342,
                "name": "Пропустить титры"
            }
        ],
        "9": [
            {
                "start": 0,
                "end": 4,
                "name": "Пропустить заставку"
            },
            {
                "start": 3178,
                "end": 3540,
                "name": "Пропустить титры"
            }
        ],
        "10": [
            {
                "start": 0,
                "end": 5,
                "name": "Пропустить заставку"
            },
            {
                "start": 3549,
                "end": 3604,
                "name": "Пропустить титры"
            }
        ],
        "11": [
            {
                "start": 0,
                "end": 6,
                "name": "Пропустить заставку"
            },
            {
                "start": 3364,
                "end": 3419,
                "name": "Пропустить титры"
            }
        ],
        "12": [
            {
                "start": 0,
                "end": 5,
                "name": "Пропустить заставку"
            },
            {
                "start": 3248,
                "end": 3323,
                "name": "Пропустить титры"
            }
        ],
        "13": [
            {
                "start": 0,
                "end": 11,
                "name": "Пропустить заставку"
            },
            {
                "start": 3593,
                "end": 3653,
                "name": "Пропустить титры"
            }
        ],
        "14": [
            {
                "start": 0,
                "end": 4,
                "name": "Пропустить заставку"
            },
            {
                "start": 3377,
                "end": 3764,
                "name": "Пропустить титры"
            }
        ]
    }
}