{
    "2": {
        "1": [
            {
                "start": 0,
                "end": 16,
                "name": "Пропустить заставку"
            },
            {
                "start": 3106,
                "end": 3169,
                "name": "Пропустить титры"
            }
        ],
        "2": [
            {
                "start": 0,
                "end": 7,
                "name": "Пропустить заставку"
            },
            {
                "start": 2859,
                "end": 2920,
                "name": "Пропустить титры"
            }
        ],
        "3": [
            {
                "start": 691,
                "end": 799,
                "name": "Пропустить заставку"
            },
            {
                "start": 2969,
                "end": 3047,
                "name": "Пропустить титры"
            }
        ],
        "4": [
            {
                "start": 0,
                "end": 10,
                "name": "Пропустить заставку"
            },
            {
                "start": 2959,
                "end": 3025,
                "name": "Пропустить титры"
            }
        ],
        "5": [
            {
                "start": 0,
                "end": 10,
                "name": "Пропустить заставку"
            },
            {
                "start": 3175,
                "end": 3269,
                "name": "Пропустить титры"
            }
        ],
        "6": [
            {
                "start": 0,
                "end": 12,
                "name": "Пропустить заставку"
            },
            {
                "start": 2767,
                "end": 2831,
                "name": "Пропустить титры"
            }
        ],
        "7": [
            {
                "start": 0,
                "end": 9,
                "name": "Пропустить заставку"
            },
            {
                "start": 3394,
                "end": 3460,
                "name": "Пропустить титры"
            }
        ],
        "8": [
            {
                "start": 0,
                "end": 7,
                "name": "Пропустить заставку"
            },
            {
                "start": 3481,
                "end": 3565,
                "name": "Пропустить титры"
            }
        ]
    }
}