{
    "1": {
        "1": [
            {
                "start": 2596,
                "end": 2629,
                "name": "Пропустить заставку"
            }
        ],
        "2": [
            {
                "start": 0,
                "end": 76,
                "name": "Пропустить заставку"
            },
            {
                "start": 2533,
                "end": 2565,
                "name": "Пропустить титры"
            }
        ],
        "3": [
            {
                "start": 0,
                "end": 62,
                "name": "Пропустить заставку"
            },
            {
                "start": 2535,
                "end": 2563,
                "name": "Пропустить титры"
            }
        ],
        "4": [
            {
                "start": 0,
                "end": 68,
                "name": "Пропустить заставку"
            },
            {
                "start": 2535,
                "end": 2562,
                "name": "Пропустить титры"
            }
        ],
        "5": [
            {
                "start": 0,
                "end": 73,
                "name": "Пропустить заставку"
            },
            {
                "start": 2529,
                "end": 2558,
                "name": "Пропустить титры"
            }
        ],
        "6": [
            {
                "start": 0,
                "end": 74,
                "name": "Пропустить заставку"
            },
            {
                "start": 2536,
                "end": 2566,
                "name": "Пропустить титры"
            }
        ],
        "7": [
            {
                "start": 0,
                "end": 64,
                "name": "Пропустить заставку"
            },
            {
                "start": 2522,
                "end": 2553,
                "name": "Пропустить титры"
            }
        ],
        "8": [
            {
                "start": 0,
                "end": 60,
                "name": "Пропустить заставку"
            },
            {
                "start": 2530,
                "end": 2557,
                "name": "Пропустить титры"
            }
        ],
        "9": [
            {
                "start": 0,
                "end": 64,
                "name": "Пропустить заставку"
            },
            {
                "start": 2535,
                "end": 2563,
                "name": "Пропустить титры"
            }
        ],
        "10": [
            {
                "start": 0,
                "end": 62,
                "name": "Пропустить заставку"
            },
            {
                "start": 2528,
                "end": 2559,
                "name": "Пропустить титры"
            }
        ],
        "11": [
            {
                "start": 0,
                "end": 66,
                "name": "Пропустить заставку"
            },
            {
                "start": 2522,
                "end": 2553,
                "name": "Пропустить титры"
            }
        ],
        "12": [
            {
                "start": 0,
                "end": 66,
                "name": "Пропустить заставку"
            },
            {
                "start": 2488,
                "end": 2520,
                "name": "Пропустить титры"
            }
        ],
        "13": [
            {
                "start": 0,
                "end": 5,
                "name": "Пропустить заставку"
            },
            {
                "start": 2534,
                "end": 2565,
                "name": "Пропустить титры"
            }
        ],
        "14": [
            {
                "start": 0,
                "end": 82,
                "name": "Пропустить заставку"
            },
            {
                "start": 2527,
                "end": 2557,
                "name": "Пропустить титры"
            }
        ],
        "15": [
            {
                "start": 0,
                "end": 68,
                "name": "Пропустить заставку"
            },
            {
                "start": 2531,
                "end": 2568,
                "name": "Пропустить титры"
            }
        ],
        "16": [
            {
                "start": 0,
                "end": 70,
                "name": "Пропустить заставку"
            },
            {
                "start": 2532,
                "end": 2561,
                "name": "Пропустить титры"
            }
        ],
        "17": [
            {
                "start": 0,
                "end": 55,
                "name": "Пропустить заставку"
            },
            {
                "start": 2536,
                "end": 2567,
                "name": "Пропустить титры"
            }
        ],
        "18": [
            {
                "start": 0,
                "end": 75,
                "name": "Пропустить заставку"
            },
            {
                "start": 2508,
                "end": 2536,
                "name": "Пропустить титры"
            }
        ],
        "19": [
            {
                "start": 0,
                "end": 106,
                "name": "Пропустить заставку"
            },
            {
                "start": 2570,
                "end": 2595,
                "name": "Пропустить титры"
            }
        ]
    },
    "2": {
        "1": [
            {
                "start": 0,
                "end": 50,
                "name": "Пропустить заставку"
            },
            {
                "start": 2582,
                "end": 2613,
                "name": "Пропустить титры"
            }
        ],
        "2": [
            {
                "start": 0,
                "end": 46,
                "name": "Пропустить заставку"
            },
            {
                "start": 2536,
                "end": 2566,
                "name": "Пропустить титры"
            }
        ],
        "3": [
            {
                "start": 0,
                "end": 58,
                "name": "Пропустить заставку"
            },
            {
                "start": 2533,
                "end": 2564,
                "name": "Пропустить титры"
            }
        ],
        "4": [
            {
                "start": 0,
                "end": 61,
                "name": "Пропустить заставку"
            },
            {
                "start": 2499,
                "end": 2529,
                "name": "Пропустить титры"
            }
        ],
        "5": [
            {
                "start": 0,
                "end": 16,
                "name": "Пропустить заставку"
            },
            {
                "start": 2587,
                "end": 2621,
                "name": "Пропустить титры"
            }
        ],
        "6": [
            {
                "start": 0,
                "end": 65,
                "name": "Пропустить заставку"
            },
            {
                "start": 2500,
                "end": 2530,
                "name": "Пропустить титры"
            }
        ]
    }
}