{
    "1": {
        "1": [
            {
                "start": 206,
                "end": 300,
                "name": "Пропустить заставку"
            },
            {
                "start": 3218,
                "end": 3357,
                "name": "Пропустить титры"
            }
        ],
        "2": [
            {
                "start": 53,
                "end": 148,
                "name": "Пропустить заставку"
            },
            {
                "start": 2793,
                "end": 2930,
                "name": "Пропустить титры"
            }
        ],
        "3": [
            {
                "start": 171,
                "end": 266,
                "name": "Пропустить заставку"
            },
            {
                "start": 2899,
                "end": 3044,
                "name": "Пропустить титры"
            }
        ],
        "4": [
            {
                "start": 0,
                "end": 93,
                "name": "Пропустить заставку"
            },
            {
                "start": 2754,
                "end": 2896,
                "name": "Пропустить титры"
            }
        ],
        "5": [
            {
                "start": 92,
                "end": 187,
                "name": "Пропустить заставку"
            },
            {
                "start": 2975,
                "end": 3116,
                "name": "Пропустить титры"
            }
        ],
        "6": [
            {
                "start": 126,
                "end": 221,
                "name": "Пропустить заставку"
            },
            {
                "start": 2844,
                "end": 2991,
                "name": "Пропустить титры"
            }
        ],
        "7": [
            {
                "start": 0,
                "end": 93,
                "name": "Пропустить заставку"
            },
            {
                "start": 3070,
                "end": 3211,
                "name": "Пропустить титры"
            }
        ],
        "8": [
            {
                "start": 0,
                "end": 93,
                "name": "Пропустить заставку"
            },
            {
                "start": 2645,
                "end": 2788,
                "name": "Пропустить титры"
            }
        ],
        "9": [
            {
                "start": 107,
                "end": 202,
                "name": "Пропустить заставку"
            },
            {
                "start": 2920,
                "end": 3061,
                "name": "Пропустить титры"
            }
        ],
        "10": [
            {
                "start": 106,
                "end": 202,
                "name": "Пропустить заставку"
            },
            {
                "start": 2980,
                "end": 3121,
                "name": "Пропустить титры"
            }
        ],
        "11": [
            {
                "start": 0,
                "end": 91,
                "name": "Пропустить заставку"
            },
            {
                "start": 3074,
                "end": 3215,
                "name": "Пропустить титры"
            }
        ],
        "12": [
            {
                "start": 117,
                "end": 213,
                "name": "Пропустить заставку"
            },
            {
                "start": 3010,
                "end": 3151,
                "name": "Пропустить титры"
            }
        ],
        "13": [
            {
                "start": 0,
                "end": 93,
                "name": "Пропустить заставку"
            },
            {
                "start": 2810,
                "end": 2950,
                "name": "Пропустить титры"
            }
        ]
    },
    "2": {
        "1": [
            {
                "start": 81,
                "end": 177,
                "name": "Пропустить заставку"
            },
            {
                "start": 2832,
                "end": 2978,
                "name": "Пропустить титры"
            }
        ],
        "2": [
            {
                "start": 178,
                "end": 273,
                "name": "Пропустить заставку"
            },
            {
                "start": 2785,
                "end": 2930,
                "name": "Пропустить титры"
            }
        ],
        "3": [
            {
                "start": 153,
                "end": 250,
                "name": "Пропустить заставку"
            },
            {
                "start": 2924,
                "end": 3065,
                "name": "Пропустить титры"
            }
        ],
        "4": [
            {
                "start": 192,
                "end": 291,
                "name": "Пропустить заставку"
            },
            {
                "start": 2729,
                "end": 2879,
                "name": "Пропустить титры"
            }
        ],
        "5": [
            {
                "start": 0,
                "end": 105,
                "name": "Пропустить заставку"
            },
            {
                "start": 2800,
                "end": 2944,
                "name": "Пропустить титры"
            }
        ],
        "6": [
            {
                "start": 151,
                "end": 248,
                "name": "Пропустить заставку"
            },
            {
                "start": 2960,
                "end": 3105,
                "name": "Пропустить титры"
            }
        ],
        "7": [
            {
                "start": 158,
                "end": 257,
                "name": "Пропустить заставку"
            },
            {
                "start": 2752,
                "end": 2899,
                "name": "Пропустить титры"
            }
        ],
        "8": [
            {
                "start": 0,
                "end": 105,
                "name": "Пропустить заставку"
            },
            {
                "start": 2692,
                "end": 2836,
                "name": "Пропустить титры"
            }
        ],
        "9": [
            {
                "start": 130,
                "end": 228,
                "name": "Пропустить заставку"
            },
            {
                "start": 2801,
                "end": 2948,
                "name": "Пропустить титры"
            }
        ],
        "10": [
            {
                "start": 305,
                "end": 400,
                "name": "Пропустить заставку"
            },
            {
                "start": 2900,
                "end": 3047,
                "name": "Пропустить титры"
            }
        ],
        "11": [
            {
                "start": 218,
                "end": 314,
                "name": "Пропустить заставку"
            },
            {
                "start": 3065,
                "end": 3206,
                "name": "Пропустить титры"
            }
        ],
        "12": [
            {
                "start": 247,
                "end": 344,
                "name": "Пропустить заставку"
            },
            {
                "start": 2680,
                "end": 2827,
                "name": "Пропустить титры"
            }
        ],
        "13": [
            {
                "start": 317,
                "end": 413,
                "name": "Пропустить заставку"
            },
            {
                "start": 3413,
                "end": 3563,
                "name": "Пропустить титры"
            }
        ]
    },
    "3": {
        "1": [
            {
                "start": 191,
                "end": 289,
                "name": "Пропустить заставку"
            },
            {
                "start": 3367,
                "end": 3507,
                "name": "Пропустить титры"
            }
        ],
        "2": [
            {
                "start": 0,
                "end": 98,
                "name": "Пропустить заставку"
            },
            {
                "start": 3120,
                "end": 3260,
                "name": "Пропустить титры"
            }
        ],
        "3": [
            {
                "start": 146,
                "end": 242,
                "name": "Пропустить заставку"
            },
            {
                "start": 2997,
                "end": 3144,
                "name": "Пропустить титры"
            }
        ],
        "4": [
            {
                "start": 2,
                "end": 99,
                "name": "Пропустить заставку"
            },
            {
                "start": 2690,
                "end": 2830,
                "name": "Пропустить титры"
            }
        ],
        "5": [
            {
                "start": 0,
                "end": 98,
                "name": "Пропустить заставку"
            },
            {
                "start": 2966,
                "end": 3105,
                "name": "Пропустить титры"
            }
        ],
        "6": [
            {
                "start": 0,
                "end": 99,
                "name": "Пропустить заставку"
            },
            {
                "start": 3081,
                "end": 3219,
                "name": "Пропустить титры"
            }
        ],
        "7": [
            {
                "start": 0,
                "end": 99,
                "name": "Пропустить заставку"
            },
            {
                "start": 3025,
                "end": 3165,
                "name": "Пропустить титры"
            }
        ],
        "8": [
            {
                "start": 0,
                "end": 100,
                "name": "Пропустить заставку"
            },
            {
                "start": 2477,
                "end": 2616,
                "name": "Пропустить титры"
            }
        ],
        "9": [
            {
                "start": 322,
                "end": 420,
                "name": "Пропустить заставку"
            },
            {
                "start": 2933,
                "end": 3072,
                "name": "Пропустить титры"
            }
        ],
        "10": [
            {
                "start": 0,
                "end": 100,
                "name": "Пропустить заставку"
            },
            {
                "start": 3258,
                "end": 3397,
                "name": "Пропустить титры"
            }
        ],
        "11": [
            {
                "start": 415,
                "end": 511,
                "name": "Пропустить заставку"
            },
            {
                "start": 2998,
                "end": 3138,
                "name": "Пропустить титры"
            }
        ],
        "12": [
            {
                "start": 0,
                "end": 100,
                "name": "Пропустить заставку"
            },
            {
                "start": 2803,
                "end": 2941,
                "name": "Пропустить титры"
            }
        ],
        "13": [
            {
                "start": 124,
                "end": 221,
                "name": "Пропустить заставку"
            },
            {
                "start": 3302,
                "end": 3444,
                "name": "Пропустить титры"
            }
        ]
    },
    "4": {
        "1": [
            {
                "start": 69,
                "end": 166,
                "name": "Пропустить заставку"
            },
            {
                "start": 2773,
                "end": 2915,
                "name": "Пропустить титры"
            }
        ],
        "2": [
            {
                "start": 0,
                "end": 99,
                "name": "Пропустить заставку"
            },
            {
                "start": 2350,
                "end": 2492,
                "name": "Пропустить титры"
            }
        ],
        "3": [
            {
                "start": 83,
                "end": 180,
                "name": "Пропустить заставку"
            },
            {
                "start": 3093,
                "end": 3237,
                "name": "Пропустить титры"
            }
        ],
        "4": [
            {
                "start": 0,
                "end": 99,
                "name": "Пропустить заставку"
            },
            {
                "start": 2400,
                "end": 2546,
                "name": "Пропустить титры"
            }
        ],
        "5": [
            {
                "start": 80,
                "end": 177,
                "name": "Пропустить заставку"
            },
            {
                "start": 2698,
                "end": 2844,
                "name": "Пропустить титры"
            }
        ],
        "6": [
            {
                "start": 0,
                "end": 100,
                "name": "Пропустить заставку"
            },
            {
                "start": 2712,
                "end": 2852,
                "name": "Пропустить титры"
            }
        ],
        "7": [
            {
                "start": 0,
                "end": 101,
                "name": "Пропустить заставку"
            },
            {
                "start": 2963,
                "end": 3105,
                "name": "Пропустить титры"
            }
        ],
        "8": [
            {
                "start": 112,
                "end": 212,
                "name": "Пропустить заставку"
            },
            {
                "start": 2628,
                "end": 2770,
                "name": "Пропустить титры"
            }
        ],
        "9": [
            {
                "start": 0,
                "end": 99,
                "name": "Пропустить заставку"
            },
            {
                "start": 2590,
                "end": 2730,
                "name": "Пропустить титры"
            }
        ],
        "10": [
            {
                "start": 0,
                "end": 101,
                "name": "Пропустить заставку"
            },
            {
                "start": 3258,
                "end": 3400,
                "name": "Пропустить титры"
            }
        ],
        "11": [
            {
                "start": 0,
                "end": 101,
                "name": "Пропустить заставку"
            },
            {
                "start": 2952,
                "end": 3094,
                "name": "Пропустить титры"
            }
        ],
        "12": [
            {
                "start": 0,
                "end": 100,
                "name": "Пропустить заставку"
            },
            {
                "start": 2625,
                "end": 2768,
                "name": "Пропустить титры"
            }
        ],
        "13": [
            {
                "start": 45,
                "end": 144,
                "name": "Пропустить заставку"
            },
            {
                "start": 3149,
                "end": 3290,
                "name": "Пропустить титры"
            }
        ]
    },
    "5": {
        "1": [
            {
                "start": 416,
                "end": 511,
                "name": "Пропустить заставку"
            },
            {
                "start": 3193,
                "end": 3331,
                "name": "Пропустить титры"
            }
        ],
        "2": [
            {
                "start": 126,
                "end": 224,
                "name": "Пропустить заставку"
            },
            {
                "start": 3019,
                "end": 3156,
                "name": "Пропустить титры"
            }
        ],
        "3": [
            {
                "start": 0,
                "end": 165,
                "name": "Пропустить заставку"
            },
            {
                "start": 3034,
                "end": 3170,
                "name": "Пропустить титры"
            }
        ],
        "4": [
            {
                "start": 0,
                "end": 169,
                "name": "Пропустить заставку"
            },
            {
                "start": 2583,
                "end": 2722,
                "name": "Пропустить титры"
            }
        ],
        "5": [
            {
                "start": 0,
                "end": 63,
                "name": "Пропустить заставку"
            },
            {
                "start": 2978,
                "end": 3115,
                "name": "Пропустить титры"
            },
            {
                "start": 252,
                "end": 353,
                "name": "Пропустить титры"
            }
        ],
        "6": [
            {
                "start": 0,
                "end": 61,
                "name": "Пропустить заставку"
            },
            {
                "start": 3207,
                "end": 3345,
                "name": "Пропустить титры"
            },
            {
                "start": 98,
                "end": 196,
                "name": "Пропустить титры"
            }
        ],
        "7": [
            {
                "start": 0,
                "end": 63,
                "name": "Пропустить заставку"
            },
            {
                "start": 2812,
                "end": 2949,
                "name": "Пропустить титры"
            },
            {
                "start": 140,
                "end": 237,
                "name": "Пропустить титры"
            }
        ],
        "8": [
            {
                "start": 0,
                "end": 63,
                "name": "Пропустить заставку"
            },
            {
                "start": 2615,
                "end": 2754,
                "name": "Пропустить титры"
            },
            {
                "start": 230,
                "end": 331,
                "name": "Пропустить титры"
            }
        ],
        "9": [
            {
                "start": 0,
                "end": 160,
                "name": "Пропустить заставку"
            },
            {
                "start": 3149,
                "end": 3287,
                "name": "Пропустить титры"
            }
        ],
        "10": [
            {
                "start": 0,
                "end": 165,
                "name": "Пропустить заставку"
            },
            {
                "start": 3275,
                "end": 3415,
                "name": "Пропустить титры"
            }
        ],
        "11": [
            {
                "start": 0,
                "end": 59,
                "name": "Пропустить заставку"
            },
            {
                "start": 2950,
                "end": 3089,
                "name": "Пропустить титры"
            },
            {
                "start": 131,
                "end": 232,
                "name": "Пропустить титры"
            }
        ],
        "12": [
            {
                "start": 0,
                "end": 62,
                "name": "Пропустить заставку"
            },
            {
                "start": 3129,
                "end": 3266,
                "name": "Пропустить титры"
            },
            {
                "start": 139,
                "end": 238,
                "name": "Пропустить титры"
            }
        ],
        "13": [
            {
                "start": 0,
                "end": 62,
                "name": "Пропустить заставку"
            },
            {
                "start": 3257,
                "end": 3392,
                "name": "Пропустить титры"
            },
            {
                "start": 131,
                "end": 233,
                "name": "Пропустить титры"
            }
        ]
    },
    "6": {
        "1": [
            {
                "start": 0,
                "end": 62,
                "name": "Пропустить заставку"
            },
            {
                "start": 3034,
                "end": 3178,
                "name": "Пропустить титры"
            },
            {
                "start": 250,
                "end": 350,
                "name": "Пропустить титры"
            }
        ],
        "2": [
            {
                "start": 0,
                "end": 64,
                "name": "Пропустить заставку"
            },
            {
                "start": 3050,
                "end": 3192,
                "name": "Пропустить титры"
            },
            {
                "start": 191,
                "end": 286,
                "name": "Пропустить титры"
            }
        ],
        "3": [
            {
                "start": 0,
                "end": 164,
                "name": "Пропустить заставку"
            },
            {
                "start": 3050,
                "end": 3188,
                "name": "Пропустить титры"
            }
        ],
        "4": [
            {
                "start": 0,
                "end": 63,
                "name": "Пропустить заставку"
            },
            {
                "start": 178,
                "end": 280,
                "name": "Пропустить титры"
            },
            {
                "start": 3048,
                "end": 3191,
                "name": "Пропустить титры"
            }
        ],
        "5": [
            {
                "start": 0,
                "end": 63,
                "name": "Пропустить заставку"
            },
            {
                "start": 3406,
                "end": 3544,
                "name": "Пропустить титры"
            },
            {
                "start": 141,
                "end": 239,
                "name": "Пропустить титры"
            }
        ],
        "6": [
            {
                "start": 0,
                "end": 63,
                "name": "Пропустить заставку"
            },
            {
                "start": 3276,
                "end": 3414,
                "name": "Пропустить титры"
            },
            {
                "start": 139,
                "end": 242,
                "name": "Пропустить титры"
            }
        ],
        "7": [
            {
                "start": 0,
                "end": 63,
                "name": "Пропустить заставку"
            },
            {
                "start": 3301,
                "end": 3437,
                "name": "Пропустить титры"
            },
            {
                "start": 228,
                "end": 325,
                "name": "Пропустить титры"
            }
        ],
        "8": [
            {
                "start": 0,
                "end": 60,
                "name": "Пропустить заставку"
            },
            {
                "start": 3187,
                "end": 3330,
                "name": "Пропустить титры"
            },
            {
                "start": 79,
                "end": 178,
                "name": "Пропустить титры"
            }
        ]
    }
}