{
    "1": {
        "1": [
            {
                "start": 0,
                "end": 17,
                "name": "Пропустить заставку"
            },
            {
                "start": 75,
                "end": 120,
                "name": "Пропустить титры"
            },
            {
                "start": 3065,
                "end": 3099,
                "name": "Пропустить титры"
            }
        ],
        "2": [
            {
                "start": 0,
                "end": 15,
                "name": "Пропустить заставку"
            },
            {
                "start": 59,
                "end": 102,
                "name": "Пропустить титры"
            },
            {
                "start": 3062,
                "end": 3096,
                "name": "Пропустить титры"
            }
        ],
        "3": [
            {
                "start": 0,
                "end": 16,
                "name": "Пропустить заставку"
            },
            {
                "start": 117,
                "end": 162,
                "name": "Пропустить титры"
            },
            {
                "start": 3065,
                "end": 3098,
                "name": "Пропустить титры"
            }
        ],
        "4": [
            {
                "start": 0,
                "end": 14,
                "name": "Пропустить заставку"
            },
            {
                "start": 164,
                "end": 207,
                "name": "Пропустить титры"
            },
            {
                "start": 3002,
                "end": 3035,
                "name": "Пропустить титры"
            }
        ],
        "5": [
            {
                "start": 0,
                "end": 17,
                "name": "Пропустить заставку"
            },
            {
                "start": 121,
                "end": 164,
                "name": "Пропустить титры"
            },
            {
                "start": 3065,
                "end": 3099,
                "name": "Пропустить титры"
            }
        ]
    }
}