{
    "1": {
        "1": [
            {
                "start": 2605,
                "end": 2654,
                "name": "Пропустить заставку"
            }
        ],
        "2": [
            {
                "start": 55,
                "end": 110,
                "name": "Пропустить заставку"
            },
            {
                "start": 2550,
                "end": 2599,
                "name": "Пропустить титры"
            }
        ],
        "3": [
            {
                "start": 108,
                "end": 167,
                "name": "Пропустить заставку"
            },
            {
                "start": 2528,
                "end": 2575,
                "name": "Пропустить титры"
            }
        ],
        "4": [
            {
                "start": 78,
                "end": 136,
                "name": "Пропустить заставку"
            },
            {
                "start": 2588,
                "end": 2635,
                "name": "Пропустить титры"
            }
        ],
        "5": [
            {
                "start": 102,
                "end": 159,
                "name": "Пропустить заставку"
            },
            {
                "start": 2480,
                "end": 2525,
                "name": "Пропустить титры"
            }
        ],
        "6": [
            {
                "start": 96,
                "end": 152,
                "name": "Пропустить заставку"
            },
            {
                "start": 2628,
                "end": 2675,
                "name": "Пропустить титры"
            }
        ],
        "7": [
            {
                "start": 137,
                "end": 192,
                "name": "Пропустить заставку"
            },
            {
                "start": 2627,
                "end": 2674,
                "name": "Пропустить титры"
            }
        ],
        "8": [
            {
                "start": 174,
                "end": 231,
                "name": "Пропустить заставку"
            },
            {
                "start": 2630,
                "end": 2677,
                "name": "Пропустить титры"
            }
        ],
        "9": [
            {
                "start": 269,
                "end": 326,
                "name": "Пропустить заставку"
            },
            {
                "start": 2626,
                "end": 2673,
                "name": "Пропустить титры"
            }
        ],
        "10": [
            {
                "start": 112,
                "end": 169,
                "name": "Пропустить заставку"
            },
            {
                "start": 2506,
                "end": 2553,
                "name": "Пропустить титры"
            }
        ],
        "11": [
            {
                "start": 150,
                "end": 208,
                "name": "Пропустить заставку"
            },
            {
                "start": 2619,
                "end": 2666,
                "name": "Пропустить титры"
            }
        ],
        "12": [
            {
                "start": 69,
                "end": 125,
                "name": "Пропустить заставку"
            },
            {
                "start": 2477,
                "end": 2525,
                "name": "Пропустить титры"
            }
        ],
        "13": [
            {
                "start": 81,
                "end": 139,
                "name": "Пропустить заставку"
            },
            {
                "start": 2348,
                "end": 2394,
                "name": "Пропустить титры"
            }
        ],
        "14": [
            {
                "start": 150,
                "end": 207,
                "name": "Пропустить заставку"
            },
            {
                "start": 2620,
                "end": 2676,
                "name": "Пропустить титры"
            }
        ],
        "15": [
            {
                "start": 269,
                "end": 328,
                "name": "Пропустить заставку"
            },
            {
                "start": 2540,
                "end": 2588,
                "name": "Пропустить титры"
            }
        ],
        "16": [
            {
                "start": 109,
                "end": 164,
                "name": "Пропустить заставку"
            },
            {
                "start": 2627,
                "end": 2674,
                "name": "Пропустить титры"
            }
        ],
        "17": [
            {
                "start": 232,
                "end": 287,
                "name": "Пропустить заставку"
            },
            {
                "start": 2625,
                "end": 2674,
                "name": "Пропустить титры"
            }
        ],
        "18": [
            {
                "start": 122,
                "end": 180,
                "name": "Пропустить заставку"
            },
            {
                "start": 2623,
                "end": 2670,
                "name": "Пропустить титры"
            }
        ],
        "19": [
            {
                "start": 137,
                "end": 194,
                "name": "Пропустить заставку"
            },
            {
                "start": 2494,
                "end": 2540,
                "name": "Пропустить титры"
            }
        ],
        "20": [
            {
                "start": 137,
                "end": 196,
                "name": "Пропустить заставку"
            },
            {
                "start": 2602,
                "end": 2648,
                "name": "Пропустить титры"
            }
        ],
        "21": [
            {
                "start": 119,
                "end": 174,
                "name": "Пропустить заставку"
            },
            {
                "start": 2593,
                "end": 2639,
                "name": "Пропустить титры"
            }
        ]
    },
    "2": {
        "1": [
            {
                "start": 72,
                "end": 127,
                "name": "Пропустить заставку"
            },
            {
                "start": 2455,
                "end": 2503,
                "name": "Пропустить титры"
            }
        ],
        "2": [
            {
                "start": 103,
                "end": 159,
                "name": "Пропустить заставку"
            },
            {
                "start": 2623,
                "end": 2670,
                "name": "Пропустить титры"
            }
        ],
        "3": [
            {
                "start": 0,
                "end": 8,
                "name": "Пропустить заставку"
            },
            {
                "start": 210,
                "end": 207,
                "name": "Пропустить титры"
            }
        ],
        "4": [
            {
                "start": 91,
                "end": 146,
                "name": "Пропустить заставку"
            },
            {
                "start": 2558,
                "end": 2606,
                "name": "Пропустить титры"
            }
        ],
        "5": [
            {
                "start": 174,
                "end": 230,
                "name": "Пропустить заставку"
            },
            {
                "start": 2629,
                "end": 2675,
                "name": "Пропустить титры"
            }
        ],
        "6": [
            {
                "start": 143,
                "end": 199,
                "name": "Пропустить заставку"
            },
            {
                "start": 2627,
                "end": 2672,
                "name": "Пропустить титры"
            }
        ],
        "7": [
            {
                "start": 139,
                "end": 197,
                "name": "Пропустить заставку"
            },
            {
                "start": 2624,
                "end": 2673,
                "name": "Пропустить титры"
            }
        ],
        "8": [
            {
                "start": 110,
                "end": 166,
                "name": "Пропустить заставку"
            },
            {
                "start": 2627,
                "end": 2675,
                "name": "Пропустить титры"
            }
        ],
        "9": [
            {
                "start": 132,
                "end": 190,
                "name": "Пропустить заставку"
            },
            {
                "start": 2627,
                "end": 2643,
                "name": "Пропустить титры"
            }
        ],
        "10": [
            {
                "start": 118,
                "end": 175,
                "name": "Пропустить заставку"
            },
            {
                "start": 2626,
                "end": 2674,
                "name": "Пропустить титры"
            }
        ],
        "11": [
            {
                "start": 139,
                "end": 200,
                "name": "Пропустить заставку"
            },
            {
                "start": 2569,
                "end": 2613,
                "name": "Пропустить титры"
            }
        ],
        "12": [
            {
                "start": 160,
                "end": 217,
                "name": "Пропустить заставку"
            },
            {
                "start": 2628,
                "end": 2675,
                "name": "Пропустить титры"
            }
        ],
        "13": [
            {
                "start": 207,
                "end": 266,
                "name": "Пропустить заставку"
            },
            {
                "start": 2541,
                "end": 2587,
                "name": "Пропустить титры"
            }
        ],
        "14": [
            {
                "start": 197,
                "end": 254,
                "name": "Пропустить заставку"
            },
            {
                "start": 2481,
                "end": 2528,
                "name": "Пропустить титры"
            }
        ],
        "15": [
            {
                "start": 65,
                "end": 120,
                "name": "Пропустить заставку"
            },
            {
                "start": 2485,
                "end": 2530,
                "name": "Пропустить титры"
            }
        ],
        "16": [
            {
                "start": 167,
                "end": 225,
                "name": "Пропустить заставку"
            },
            {
                "start": 2638,
                "end": 2684,
                "name": "Пропустить титры"
            }
        ],
        "17": [
            {
                "start": 77,
                "end": 133,
                "name": "Пропустить заставку"
            },
            {
                "start": 2617,
                "end": 2663,
                "name": "Пропустить титры"
            }
        ],
        "18": [
            {
                "start": 92,
                "end": 150,
                "name": "Пропустить заставку"
            },
            {
                "start": 2598,
                "end": 2646,
                "name": "Пропустить титры"
            }
        ],
        "19": [
            {
                "start": 185,
                "end": 242,
                "name": "Пропустить заставку"
            },
            {
                "start": 2615,
                "end": 2670,
                "name": "Пропустить титры"
            }
        ],
        "20": [
            {
                "start": 125,
                "end": 181,
                "name": "Пропустить заставку"
            },
            {
                "start": 2558,
                "end": 2604,
                "name": "Пропустить титры"
            }
        ],
        "21": [
            {
                "start": 125,
                "end": 182,
                "name": "Пропустить заставку"
            },
            {
                "start": 2527,
                "end": 2572,
                "name": "Пропустить титры"
            }
        ],
        "22": [
            {
                "start": 164,
                "end": 220,
                "name": "Пропустить заставку"
            },
            {
                "start": 2655,
                "end": 2701,
                "name": "Пропустить титры"
            }
        ]
    },
    "3": {
        "1": [
            {
                "start": 312,
                "end": 368,
                "name": "Пропустить заставку"
            },
            {
                "start": 2618,
                "end": 2664,
                "name": "Пропустить титры"
            }
        ],
        "2": [
            {
                "start": 151,
                "end": 209,
                "name": "Пропустить заставку"
            },
            {
                "start": 2566,
                "end": 2611,
                "name": "Пропустить титры"
            }
        ],
        "3": [
            {
                "start": 81,
                "end": 136,
                "name": "Пропустить заставку"
            },
            {
                "start": 2593,
                "end": 2641,
                "name": "Пропустить титры"
            }
        ],
        "4": [
            {
                "start": 152,
                "end": 208,
                "name": "Пропустить заставку"
            },
            {
                "start": 2446,
                "end": 2491,
                "name": "Пропустить титры"
            }
        ],
        "5": [
            {
                "start": 185,
                "end": 241,
                "name": "Пропустить заставку"
            },
            {
                "start": 2556,
                "end": 2602,
                "name": "Пропустить титры"
            }
        ],
        "6": [
            {
                "start": 121,
                "end": 177,
                "name": "Пропустить заставку"
            },
            {
                "start": 2445,
                "end": 2492,
                "name": "Пропустить титры"
            }
        ],
        "7": [
            {
                "start": 158,
                "end": 213,
                "name": "Пропустить заставку"
            },
            {
                "start": 2564,
                "end": 2619,
                "name": "Пропустить титры"
            }
        ],
        "8": [
            {
                "start": 87,
                "end": 147,
                "name": "Пропустить заставку"
            },
            {
                "start": 2622,
                "end": 2668,
                "name": "Пропустить титры"
            }
        ],
        "9": [
            {
                "start": 61,
                "end": 115,
                "name": "Пропустить заставку"
            },
            {
                "start": 2453,
                "end": 2499,
                "name": "Пропустить титры"
            }
        ],
        "10": [
            {
                "start": 81,
                "end": 137,
                "name": "Пропустить заставку"
            },
            {
                "start": 2502,
                "end": 2546,
                "name": "Пропустить титры"
            }
        ],
        "11": [
            {
                "start": 196,
                "end": 251,
                "name": "Пропустить заставку"
            },
            {
                "start": 2447,
                "end": 2495,
                "name": "Пропустить титры"
            }
        ],
        "12": [
            {
                "start": 151,
                "end": 206,
                "name": "Пропустить заставку"
            },
            {
                "start": 2570,
                "end": 2617,
                "name": "Пропустить титры"
            }
        ],
        "13": [
            {
                "start": 140,
                "end": 197,
                "name": "Пропустить заставку"
            },
            {
                "start": 2430,
                "end": 2487,
                "name": "Пропустить титры"
            }
        ],
        "14": [
            {
                "start": 232,
                "end": 286,
                "name": "Пропустить заставку"
            },
            {
                "start": 2620,
                "end": 2665,
                "name": "Пропустить титры"
            }
        ],
        "15": [
            {
                "start": 159,
                "end": 215,
                "name": "Пропустить заставку"
            },
            {
                "start": 2609,
                "end": 2656,
                "name": "Пропустить титры"
            }
        ],
        "16": [
            {
                "start": 105,
                "end": 161,
                "name": "Пропустить заставку"
            },
            {
                "start": 2615,
                "end": 2665,
                "name": "Пропустить титры"
            }
        ],
        "17": [
            {
                "start": 191,
                "end": 245,
                "name": "Пропустить заставку"
            },
            {
                "start": 2618,
                "end": 2666,
                "name": "Пропустить титры"
            }
        ],
        "18": [
            {
                "start": 158,
                "end": 214,
                "name": "Пропустить заставку"
            },
            {
                "start": 2622,
                "end": 2670,
                "name": "Пропустить титры"
            }
        ],
        "19": [
            {
                "start": 159,
                "end": 215,
                "name": "Пропустить заставку"
            },
            {
                "start": 2579,
                "end": 2623,
                "name": "Пропустить титры"
            }
        ],
        "20": [
            {
                "start": 144,
                "end": 201,
                "name": "Пропустить заставку"
            },
            {
                "start": 2622,
                "end": 2668,
                "name": "Пропустить титры"
            }
        ],
        "21": [
            {
                "start": 126,
                "end": 181,
                "name": "Пропустить заставку"
            },
            {
                "start": 2586,
                "end": 2632,
                "name": "Пропустить титры"
            }
        ],
        "22": [
            {
                "start": 154,
                "end": 211,
                "name": "Пропустить заставку"
            },
            {
                "start": 2624,
                "end": 2670,
                "name": "Пропустить титры"
            }
        ]
    },
    "4": {
        "1": [
            {
                "start": 243,
                "end": 299,
                "name": "Пропустить заставку"
            },
            {
                "start": 2581,
                "end": 2627,
                "name": "Пропустить титры"
            }
        ],
        "2": [
            {
                "start": 0,
                "end": 60,
                "name": "Пропустить заставку"
            },
            {
                "start": 200,
                "end": 254,
                "name": "Пропустить титры"
            },
            {
                "start": 2489,
                "end": 2532,
                "name": "Пропустить титры"
            }
        ],
        "3": [
            {
                "start": 143,
                "end": 200,
                "name": "Пропустить заставку"
            },
            {
                "start": 2613,
                "end": 2657,
                "name": "Пропустить титры"
            }
        ],
        "4": [
            {
                "start": 168,
                "end": 224,
                "name": "Пропустить заставку"
            },
            {
                "start": 2610,
                "end": 2657,
                "name": "Пропустить титры"
            }
        ],
        "5": [
            {
                "start": 137,
                "end": 191,
                "name": "Пропустить заставку"
            },
            {
                "start": 2619,
                "end": 2664,
                "name": "Пропустить титры"
            }
        ],
        "6": [
            {
                "start": 116,
                "end": 173,
                "name": "Пропустить заставку"
            },
            {
                "start": 2602,
                "end": 2657,
                "name": "Пропустить титры"
            }
        ],
        "7": [
            {
                "start": 109,
                "end": 164,
                "name": "Пропустить заставку"
            },
            {
                "start": 2620,
                "end": 2666,
                "name": "Пропустить титры"
            }
        ],
        "8": [
            {
                "start": 0,
                "end": 63,
                "name": "Пропустить заставку"
            },
            {
                "start": 2594,
                "end": 2639,
                "name": "Пропустить титры"
            }
        ],
        "9": [
            {
                "start": 0,
                "end": 23,
                "name": "Пропустить заставку"
            },
            {
                "start": 2620,
                "end": 2662,
                "name": "Пропустить титры"
            },
            {
                "start": 252,
                "end": 307,
                "name": "Пропустить титры"
            }
        ],
        "10": [
            {
                "start": 0,
                "end": 61,
                "name": "Пропустить заставку"
            },
            {
                "start": 2595,
                "end": 2638,
                "name": "Пропустить титры"
            },
            {
                "start": 197,
                "end": 251,
                "name": "Пропустить титры"
            }
        ],
        "11": [
            {
                "start": 0,
                "end": 22,
                "name": "Пропустить заставку"
            },
            {
                "start": 2592,
                "end": 2636,
                "name": "Пропустить титры"
            },
            {
                "start": 280,
                "end": 333,
                "name": "Пропустить титры"
            }
        ],
        "12": [
            {
                "start": 241,
                "end": 296,
                "name": "Пропустить заставку"
            },
            {
                "start": 2586,
                "end": 2632,
                "name": "Пропустить титры"
            }
        ],
        "13": [
            {
                "start": 0,
                "end": 45,
                "name": "Пропустить заставку"
            },
            {
                "start": 2592,
                "end": 2635,
                "name": "Пропустить титры"
            },
            {
                "start": 192,
                "end": 248,
                "name": "Пропустить титры"
            }
        ],
        "14": [
            {
                "start": 156,
                "end": 213,
                "name": "Пропустить заставку"
            },
            {
                "start": 2592,
                "end": 2636,
                "name": "Пропустить титры"
            }
        ],
        "15": [
            {
                "start": 0,
                "end": 80,
                "name": "Пропустить заставку"
            },
            {
                "start": 2433,
                "end": 2477,
                "name": "Пропустить титры"
            },
            {
                "start": 289,
                "end": 344,
                "name": "Пропустить титры"
            }
        ],
        "16": [
            {
                "start": 151,
                "end": 206,
                "name": "Пропустить заставку"
            },
            {
                "start": 2586,
                "end": 2633,
                "name": "Пропустить титры"
            }
        ],
        "17": [
            {
                "start": 122,
                "end": 181,
                "name": "Пропустить заставку"
            },
            {
                "start": 2556,
                "end": 2605,
                "name": "Пропустить титры"
            }
        ],
        "18": [
            {
                "start": 0,
                "end": 62,
                "name": "Пропустить заставку"
            },
            {
                "start": 2579,
                "end": 2624,
                "name": "Пропустить титры"
            },
            {
                "start": 229,
                "end": 285,
                "name": "Пропустить титры"
            }
        ],
        "19": [
            {
                "start": 0,
                "end": 36,
                "name": "Пропустить заставку"
            },
            {
                "start": 2587,
                "end": 2633,
                "name": "Пропустить титры"
            },
            {
                "start": 233,
                "end": 287,
                "name": "Пропустить титры"
            }
        ],
        "20": [
            {
                "start": 109,
                "end": 163,
                "name": "Пропустить заставку"
            },
            {
                "start": 2590,
                "end": 2636,
                "name": "Пропустить титры"
            }
        ],
        "21": [
            {
                "start": 88,
                "end": 143,
                "name": "Пропустить заставку"
            },
            {
                "start": 2583,
                "end": 2629,
                "name": "Пропустить титры"
            }
        ],
        "22": [
            {
                "start": 68,
                "end": 123,
                "name": "Пропустить заставку"
            },
            {
                "start": 2587,
                "end": 2632,
                "name": "Пропустить титры"
            }
        ]
    },
    "5": {
        "1": [
            {
                "start": 0,
                "end": 34,
                "name": "Пропустить заставку"
            },
            {
                "start": 2589,
                "end": 2636,
                "name": "Пропустить титры"
            }
        ],
        "2": [
            {
                "start": 0,
                "end": 61,
                "name": "Пропустить заставку"
            },
            {
                "start": 2458,
                "end": 2502,
                "name": "Пропустить титры"
            },
            {
                "start": 95,
                "end": 150,
                "name": "Пропустить титры"
            }
        ],
        "3": [
            {
                "start": 231,
                "end": 286,
                "name": "Пропустить заставку"
            },
            {
                "start": 2590,
                "end": 2636,
                "name": "Пропустить титры"
            },
            {
                "start": 0,
                "end": 18,
                "name": "Пропустить титры"
            }
        ],
        "4": [
            {
                "start": 151,
                "end": 205,
                "name": "Пропустить заставку"
            },
            {
                "start": 2586,
                "end": 2629,
                "name": "Пропустить титры"
            }
        ],
        "5": [
            {
                "start": 0,
                "end": 62,
                "name": "Пропустить заставку"
            },
            {
                "start": 2545,
                "end": 2590,
                "name": "Пропустить титры"
            },
            {
                "start": 199,
                "end": 254,
                "name": "Пропустить титры"
            }
        ],
        "6": [
            {
                "start": 127,
                "end": 183,
                "name": "Пропустить заставку"
            },
            {
                "start": 2592,
                "end": 2636,
                "name": "Пропустить титры"
            }
        ],
        "7": [
            {
                "start": 0,
                "end": 62,
                "name": "Пропустить заставку"
            },
            {
                "start": 2577,
                "end": 2621,
                "name": "Пропустить титры"
            },
            {
                "start": 212,
                "end": 266,
                "name": "Пропустить титры"
            }
        ],
        "8": [
            {
                "start": 0,
                "end": 35,
                "name": "Пропустить заставку"
            },
            {
                "start": 2587,
                "end": 2632,
                "name": "Пропустить титры"
            },
            {
                "start": 308,
                "end": 364,
                "name": "Пропустить титры"
            }
        ],
        "9": [
            {
                "start": 95,
                "end": 149,
                "name": "Пропустить заставку"
            },
            {
                "start": 2586,
                "end": 2632,
                "name": "Пропустить титры"
            }
        ],
        "10": [
            {
                "start": 100,
                "end": 156,
                "name": "Пропустить заставку"
            },
            {
                "start": 2588,
                "end": 2632,
                "name": "Пропустить титры"
            }
        ],
        "11": [
            {
                "start": 0,
                "end": 57,
                "name": "Пропустить заставку"
            },
            {
                "start": 2588,
                "end": 2632,
                "name": "Пропустить титры"
            },
            {
                "start": 165,
                "end": 220,
                "name": "Пропустить титры"
            }
        ],
        "12": [
            {
                "start": 144,
                "end": 200,
                "name": "Пропустить заставку"
            },
            {
                "start": 2580,
                "end": 2627,
                "name": "Пропустить титры"
            }
        ],
        "13": [
            {
                "start": 0,
                "end": 22,
                "name": "Пропустить заставку"
            },
            {
                "start": 2589,
                "end": 2632,
                "name": "Пропустить титры"
            },
            {
                "start": 160,
                "end": 215,
                "name": "Пропустить титры"
            }
        ],
        "14": [
            {
                "start": 0,
                "end": 57,
                "name": "Пропустить заставку"
            },
            {
                "start": 2496,
                "end": 2540,
                "name": "Пропустить титры"
            },
            {
                "start": 157,
                "end": 212,
                "name": "Пропустить титры"
            }
        ],
        "15": [
            {
                "start": 140,
                "end": 196,
                "name": "Пропустить заставку"
            },
            {
                "start": 2590,
                "end": 2632,
                "name": "Пропустить титры"
            }
        ],
        "16": [
            {
                "start": 0,
                "end": 46,
                "name": "Пропустить заставку"
            },
            {
                "start": 2588,
                "end": 2631,
                "name": "Пропустить титры"
            }
        ],
        "17": [
            {
                "start": 105,
                "end": 159,
                "name": "Пропустить заставку"
            },
            {
                "start": 2570,
                "end": 2614,
                "name": "Пропустить титры"
            }
        ],
        "18": [
            {
                "start": 90,
                "end": 145,
                "name": "Пропустить заставку"
            },
            {
                "start": 2572,
                "end": 2615,
                "name": "Пропустить титры"
            }
        ],
        "19": [
            {
                "start": 178,
                "end": 234,
                "name": "Пропустить заставку"
            },
            {
                "start": 2586,
                "end": 2631,
                "name": "Пропустить титры"
            }
        ],
        "20": [
            {
                "start": 33,
                "end": 89,
                "name": "Пропустить заставку"
            },
            {
                "start": 2588,
                "end": 2631,
                "name": "Пропустить титры"
            }
        ],
        "21": [
            {
                "start": 101,
                "end": 155,
                "name": "Пропустить заставку"
            },
            {
                "start": 2584,
                "end": 2627,
                "name": "Пропустить титры"
            }
        ],
        "22": [
            {
                "start": 166,
                "end": 222,
                "name": "Пропустить заставку"
            },
            {
                "start": 2590,
                "end": 2632,
                "name": "Пропустить титры"
            }
        ]
    },
    "6": {
        "1": [
            {
                "start": 360,
                "end": 418,
                "name": "Пропустить заставку"
            },
            {
                "start": 2580,
                "end": 2623,
                "name": "Пропустить титры"
            }
        ],
        "2": [
            {
                "start": 0,
                "end": 46,
                "name": "Пропустить заставку"
            },
            {
                "start": 2588,
                "end": 2633,
                "name": "Пропустить титры"
            },
            {
                "start": 139,
                "end": 195,
                "name": "Пропустить титры"
            }
        ],
        "3": [
            {
                "start": 261,
                "end": 316,
                "name": "Пропустить заставку"
            },
            {
                "start": 2601,
                "end": 2649,
                "name": "Пропустить титры"
            }
        ],
        "4": [
            {
                "start": 169,
                "end": 223,
                "name": "Пропустить заставку"
            },
            {
                "start": 2593,
                "end": 2641,
                "name": "Пропустить титры"
            }
        ],
        "5": [
            {
                "start": 0,
                "end": 42,
                "name": "Пропустить заставку"
            },
            {
                "start": 2596,
                "end": 2642,
                "name": "Пропустить титры"
            }
        ],
        "6": [
            {
                "start": 0,
                "end": 53,
                "name": "Пропустить заставку"
            },
            {
                "start": 2600,
                "end": 2641,
                "name": "Пропустить титры"
            },
            {
                "start": 280,
                "end": 336,
                "name": "Пропустить титры"
            }
        ],
        "7": [
            {
                "start": 4,
                "end": 51,
                "name": "Пропустить заставку"
            },
            {
                "start": 2557,
                "end": 2605,
                "name": "Пропустить титры"
            },
            {
                "start": 189,
                "end": 244,
                "name": "Пропустить титры"
            }
        ],
        "8": [
            {
                "start": 0,
                "end": 33,
                "name": "Пропустить заставку"
            },
            {
                "start": 2594,
                "end": 2643,
                "name": "Пропустить титры"
            },
            {
                "start": 175,
                "end": 229,
                "name": "Пропустить титры"
            }
        ],
        "9": [
            {
                "start": 0,
                "end": 33,
                "name": "Пропустить заставку"
            },
            {
                "start": 254,
                "end": 309,
                "name": "Пропустить титры"
            },
            {
                "start": 2597,
                "end": 2644,
                "name": "Пропустить титры"
            }
        ],
        "10": [
            {
                "start": 0,
                "end": 47,
                "name": "Пропустить заставку"
            },
            {
                "start": 2502,
                "end": 2549,
                "name": "Пропустить титры"
            },
            {
                "start": 291,
                "end": 346,
                "name": "Пропустить титры"
            }
        ],
        "11": [
            {
                "start": 214,
                "end": 268,
                "name": "Пропустить заставку"
            },
            {
                "start": 2594,
                "end": 2644,
                "name": "Пропустить титры"
            }
        ],
        "12": [
            {
                "start": 0,
                "end": 48,
                "name": "Пропустить заставку"
            },
            {
                "start": 2560,
                "end": 2607,
                "name": "Пропустить титры"
            },
            {
                "start": 285,
                "end": 340,
                "name": "Пропустить титры"
            }
        ],
        "13": [
            {
                "start": 132,
                "end": 187,
                "name": "Пропустить заставку"
            },
            {
                "start": 2604,
                "end": 2643,
                "name": "Пропустить титры"
            }
        ],
        "14": [
            {
                "start": 0,
                "end": 63,
                "name": "Пропустить заставку"
            },
            {
                "start": 287,
                "end": 340,
                "name": "Пропустить титры"
            },
            {
                "start": 2518,
                "end": 2563,
                "name": "Пропустить титры"
            }
        ],
        "15": [
            {
                "start": 0,
                "end": 93,
                "name": "Пропустить заставку"
            },
            {
                "start": 2466,
                "end": 2513,
                "name": "Пропустить титры"
            },
            {
                "start": 304,
                "end": 359,
                "name": "Пропустить титры"
            }
        ],
        "16": [
            {
                "start": 172,
                "end": 226,
                "name": "Пропустить заставку"
            },
            {
                "start": 2594,
                "end": 2640,
                "name": "Пропустить титры"
            }
        ],
        "17": [
            {
                "start": 0,
                "end": 52,
                "name": "Пропустить заставку"
            },
            {
                "start": 2584,
                "end": 2630,
                "name": "Пропустить титры"
            },
            {
                "start": 351,
                "end": 406,
                "name": "Пропустить титры"
            }
        ],
        "18": [
            {
                "start": 0,
                "end": 68,
                "name": "Пропустить заставку"
            },
            {
                "start": 2432,
                "end": 2478,
                "name": "Пропустить титры"
            },
            {
                "start": 193,
                "end": 248,
                "name": "Пропустить титры"
            }
        ],
        "19": [
            {
                "start": 0,
                "end": 50,
                "name": "Пропустить заставку"
            },
            {
                "start": 2598,
                "end": 2644,
                "name": "Пропустить титры"
            },
            {
                "start": 243,
                "end": 299,
                "name": "Пропустить титры"
            }
        ],
        "20": [
            {
                "start": 0,
                "end": 63,
                "name": "Пропустить заставку"
            },
            {
                "start": 2567,
                "end": 2612,
                "name": "Пропустить титры"
            },
            {
                "start": 200,
                "end": 256,
                "name": "Пропустить титры"
            }
        ],
        "21": [
            {
                "start": 0,
                "end": 37,
                "name": "Пропустить заставку"
            },
            {
                "start": 2596,
                "end": 2643,
                "name": "Пропустить титры"
            },
            {
                "start": 273,
                "end": 329,
                "name": "Пропустить титры"
            }
        ],
        "22": [
            {
                "start": 59,
                "end": 114,
                "name": "Пропустить заставку"
            },
            {
                "start": 2595,
                "end": 2643,
                "name": "Пропустить титры"
            }
        ]
    },
    "7": {
        "1": [
            {
                "start": 0,
                "end": 36,
                "name": "Пропустить заставку"
            },
            {
                "start": 2525,
                "end": 2563,
                "name": "Пропустить титры"
            },
            {
                "start": 156,
                "end": 212,
                "name": "Пропустить титры"
            }
        ],
        "2": [
            {
                "start": 0,
                "end": 30,
                "name": "Пропустить заставку"
            },
            {
                "start": 2527,
                "end": 2569,
                "name": "Пропустить титры"
            },
            {
                "start": 86,
                "end": 143,
                "name": "Пропустить титры"
            }
        ],
        "3": [
            {
                "start": 279,
                "end": 335,
                "name": "Пропустить заставку"
            },
            {
                "start": 2517,
                "end": 2551,
                "name": "Пропустить титры"
            }
        ],
        "4": [
            {
                "start": 5,
                "end": 48,
                "name": "Пропустить заставку"
            },
            {
                "start": 2515,
                "end": 2552,
                "name": "Пропустить титры"
            },
            {
                "start": 326,
                "end": 381,
                "name": "Пропустить титры"
            }
        ],
        "5": [
            {
                "start": 0,
                "end": 48,
                "name": "Пропустить заставку"
            },
            {
                "start": 2486,
                "end": 2521,
                "name": "Пропустить титры"
            },
            {
                "start": 141,
                "end": 196,
                "name": "Пропустить титры"
            }
        ],
        "6": [
            {
                "start": 62,
                "end": 121,
                "name": "Пропустить заставку"
            },
            {
                "start": 2511,
                "end": 2548,
                "name": "Пропустить титры"
            }
        ],
        "7": [
            {
                "start": 0,
                "end": 39,
                "name": "Пропустить заставку"
            },
            {
                "start": 2431,
                "end": 2467,
                "name": "Пропустить титры"
            },
            {
                "start": 137,
                "end": 193,
                "name": "Пропустить титры"
            }
        ],
        "8": [
            {
                "start": 257,
                "end": 312,
                "name": "Пропустить заставку"
            },
            {
                "start": 2524,
                "end": 2560,
                "name": "Пропустить титры"
            }
        ],
        "9": [
            {
                "start": 175,
                "end": 231,
                "name": "Пропустить заставку"
            },
            {
                "start": 2532,
                "end": 2570,
                "name": "Пропустить титры"
            }
        ],
        "10": [
            {
                "start": 138,
                "end": 192,
                "name": "Пропустить заставку"
            },
            {
                "start": 2448,
                "end": 2483,
                "name": "Пропустить титры"
            }
        ],
        "11": [
            {
                "start": 8,
                "end": 40,
                "name": "Пропустить заставку"
            },
            {
                "start": 234,
                "end": 288,
                "name": "Пропустить титры"
            },
            {
                "start": 2472,
                "end": 2507,
                "name": "Пропустить титры"
            }
        ],
        "12": [
            {
                "start": 102,
                "end": 157,
                "name": "Пропустить заставку"
            },
            {
                "start": 2526,
                "end": 2560,
                "name": "Пропустить титры"
            }
        ],
        "13": [
            {
                "start": 0,
                "end": 47,
                "name": "Пропустить заставку"
            },
            {
                "start": 2498,
                "end": 2532,
                "name": "Пропустить титры"
            }
        ],
        "14": [
            {
                "start": 219,
                "end": 275,
                "name": "Пропустить заставку"
            },
            {
                "start": 2508,
                "end": 2541,
                "name": "Пропустить титры"
            }
        ],
        "15": [
            {
                "start": 238,
                "end": 293,
                "name": "Пропустить заставку"
            },
            {
                "start": 2521,
                "end": 2557,
                "name": "Пропустить титры"
            }
        ],
        "16": [
            {
                "start": 232,
                "end": 288,
                "name": "Пропустить заставку"
            },
            {
                "start": 2490,
                "end": 2525,
                "name": "Пропустить титры"
            }
        ],
        "17": [
            {
                "start": 175,
                "end": 231,
                "name": "Пропустить заставку"
            },
            {
                "start": 2459,
                "end": 2493,
                "name": "Пропустить титры"
            }
        ],
        "18": [
            {
                "start": 138,
                "end": 192,
                "name": "Пропустить заставку"
            },
            {
                "start": 2485,
                "end": 2523,
                "name": "Пропустить титры"
            }
        ],
        "19": [
            {
                "start": 143,
                "end": 198,
                "name": "Пропустить заставку"
            },
            {
                "start": 2497,
                "end": 2533,
                "name": "Пропустить титры"
            }
        ],
        "20": [
            {
                "start": 172,
                "end": 228,
                "name": "Пропустить заставку"
            },
            {
                "start": 2524,
                "end": 2560,
                "name": "Пропустить титры"
            }
        ],
        "21": [
            {
                "start": 232,
                "end": 287,
                "name": "Пропустить заставку"
            },
            {
                "start": 2461,
                "end": 2500,
                "name": "Пропустить титры"
            }
        ],
        "22": [
            {
                "start": 219,
                "end": 276,
                "name": "Пропустить заставку"
            },
            {
                "start": 2512,
                "end": 2554,
                "name": "Пропустить титры"
            }
        ]
    }
}